Workbook

Sheet Assumptions
A1: Franklin's Bagels — DCF Model · Fitler MBA S06
A2: All figures $ thousands. These are course projections — assumptions to stress, not facts.
A4: LEGEND
A5: Blue text = input you can change
A6: Black text = formula (leave alone)
A7: Green text = pulled from another tab
A8: Yellow fill = the big levers — start your experiments here
A10: OPERATING ASSUMPTIONS
B11: Yr 1 | C11: Yr 2 | D11: Yr 3 | E11: Yr 4 | F11: Yr 5
A12: Revenue ($K) | B12: 780 | C12: 850 | D12: 1150 | E12: 1650 | F12: 1950
A13: EBITDA margin | B13: 0.15 | C13: 0.16 | D13: 0.14 | E13: 0.16 | F13: 0.18
A14: Capex ($K) | B14: 15 | C14: 15 | D14: 210 | E14: 35 | F14: 40
A15: Increase in working capital ($K) | B15: 7 | C15: 6 | D15: 21 | E15: 24 | F15: 21
A16: Yr 3 story: second location — buildout capex plus pre-opening staff compress the margin.
A18: VALUATION LEVERS
A19: Discount rate (r) | B19: 0.2 | C19: The room argued to 20% off the Spectrum of Returns.
A20: Exit multiple (× Yr-5 free cash flow) | B20: 5 | C20: Deliberately round. Attack it.
A21: Asking price today ($K) | B21: 700 | C21: Franklin's ask — drives the IRR.

Sheet P&L
A1: Projected P&L ($K)
A2: Simplified for teaching: EBITDA is the operating story. Depreciation, interest, and taxes are set aside tonight — see Annotations.
B4: Yr 1 | C4: Yr 2 | D4: Yr 3 | E4: Yr 4 | F4: Yr 5
A5: Revenue | B5: =Assumptions!B12 -> 780 | C5: =Assumptions!C12 -> 850 | D5: =Assumptions!D12 -> 1150 | E5: =Assumptions!E12 -> 1650 | F5: =Assumptions!F12 -> 1950
A6: Operating costs | B6: =B5-B7 -> 663 | C6: =C5-C7 -> 714 | D6: =D5-D7 -> 989 | E6: =E5-E7 -> 1386 | F6: =F5-F7 -> 1599
A7: EBITDA | B7: =B5*Assumptions!B13 -> 117 | C7: =C5*Assumptions!C13 -> 136 | D7: =D5*Assumptions!D13 -> 161 | E7: =E5*Assumptions!E13 -> 264 | F7: =F5*Assumptions!F13 -> 351
A9: Operating costs are the plug: revenue minus EBITDA. In your own model, build them bottom-up (flour, labor, rent).

Sheet Cash Flow
A1: Free Cash Flow ($K)
A2: What the business actually hands you each year — the raw material of the valuation.
B4: Yr 1 | C4: Yr 2 | D4: Yr 3 | E4: Yr 4 | F4: Yr 5
A5: EBITDA | B5: ='P&L'!B7 -> 117 | C5: ='P&L'!C7 -> 136 | D5: ='P&L'!D7 -> 161 | E5: ='P&L'!E7 -> 264 | F5: ='P&L'!F7 -> 351
A6: Less: capex | B6: =-Assumptions!B14 -> -15 | C6: =-Assumptions!C14 -> -15 | D6: =-Assumptions!D14 -> -210 | E6: =-Assumptions!E14 -> -35 | F6: =-Assumptions!F14 -> -40
A7: Less: increase in working capital | B7: =-Assumptions!B15 -> -7 | C7: =-Assumptions!C15 -> -6 | D7: =-Assumptions!D15 -> -21 | E7: =-Assumptions!E15 -> -24 | F7: =-Assumptions!F15 -> -21
A8: Free cash flow | B8: =B5+B6+B7 -> 95 | C8: =C5+C6+C7 -> 115 | D8: =D5+D6+D7 -> -70 | E8: =E5+E6+E7 -> 205 | F8: =F5+F6+F7 -> 290

Sheet Valuation
A1: Valuation — the machine, assembled
A2: Change the yellow levers on Assumptions and watch every number here repaint.
B4: Yr 1 | C4: Yr 2 | D4: Yr 3 | E4: Yr 4 | F4: Yr 5 | I4: Composition
A5: Free cash flow | B5: ='Cash Flow'!B8 -> 95 | C5: ='Cash Flow'!C8 -> 115 | D5: ='Cash Flow'!D8 -> -70 | E5: ='Cash Flow'!E8 -> 205 | F5: ='Cash Flow'!F8 -> 290 | I5: Five years of bagels | J5: =B9 -> 333.9249
A6: Discount factor 1/(1+r)^n | B6: =1/(1+Assumptions!$B$19)^1 -> 0.83333333 | C6: =1/(1+Assumptions!$B$19)^2 -> 0.69444444 | D6: =1/(1+Assumptions!$B$19)^3 -> 0.5787037 | E6: =1/(1+Assumptions!$B$19)^4 -> 0.48225309 | F6: =1/(1+Assumptions!$B$19)^5 -> 0.40187757 | I6: The sale (PV of terminal) | J6: =B11 -> 582.72248
A7: Present value | B7: =B5*B6 -> 79.166667 | C7: =C5*C6 -> 79.861111 | D7: =D5*D6 -> -40.509259 | E7: =E5*E6 -> 98.861883 | F7: =F5*F6 -> 116.5445
A9: Sum of PVs — five years of bagels | B9: =SUM(B7:F7) -> 333.9249
A10: Terminal value at Yr 5 (multiple × Yr-5 FCF) | B10: =Assumptions!$B$20*F5 -> 1450
A11: PV of terminal value — the sale | B11: =B10*F6 -> 582.72248
A12: NET PRESENT VALUE | B12: =B9+B11 -> 916.64738
A13: Terminal value share of NPV — the lab coat | B13: =B11/B12 -> 0.63571063
A15: IRR — the answer's twin
A16: Cash flows if you buy at the asking price | B16: =-Assumptions!$B$21 -> -700 | C16: =B5 -> 95 | D16: =C5 -> 115 | E16: =D5 -> -70 | F16: =E5 -> 205 | G16: =F5+B10 -> 1740
A17: IRR — what the stream pays at that price | B17: =IRR(B16:G16) -> 0.2773301 | C17: Yr-5 entry combines final year's cash and the sale.
A20: SENSITIVITY — NPV ($K) across the two big assumptions
A21: Rows: discount rate. Columns: exit multiple. Every cell is a live formula — no lookup tables, no magic.
A23: r \ multiple | B23: 3 | C23: 4 | D23: 5 | E23: 6 | F23: 7
A24: 0.1 | B24: =$B$5/(1+$A24)^1+$C$5/(1+$A24)^2+$D$5/(1+$A24)^3+$E$5/(1+$A24)^4+($F$5+B$23*$F$5)/(1+$A24)^5 -> 989.09942 | C24: =$B$5/(1+$A24)^1+$C$5/(1+$A24)^2+$D$5/(1+$A24)^3+$E$5/(1+$A24)^4+($F$5+C$23*$F$5)/(1+$A24)^5 -> 1169.1666 | D24: =$B$5/(1+$A24)^1+$C$5/(1+$A24)^2+$D$5/(1+$A24)^3+$E$5/(1+$A24)^4+($F$5+D$23*$F$5)/(1+$A24)^5 -> 1349.2338 | E24: =$B$5/(1+$A24)^1+$C$5/(1+$A24)^2+$D$5/(1+$A24)^3+$E$5/(1+$A24)^4+($F$5+E$23*$F$5)/(1+$A24)^5 -> 1529.301 | F24: =$B$5/(1+$A24)^1+$C$5/(1+$A24)^2+$D$5/(1+$A24)^3+$E$5/(1+$A24)^4+($F$5+F$23*$F$5)/(1+$A24)^5 -> 1709.3682
A25: 0.15 | B25: =$B$5/(1+$A25)^1+$C$5/(1+$A25)^2+$D$5/(1+$A25)^3+$E$5/(1+$A25)^4+($F$5+B$23*$F$5)/(1+$A25)^5 -> 817.47351 | C25: =$B$5/(1+$A25)^1+$C$5/(1+$A25)^2+$D$5/(1+$A25)^3+$E$5/(1+$A25)^4+($F$5+C$23*$F$5)/(1+$A25)^5 -> 961.65476 | D25: =$B$5/(1+$A25)^1+$C$5/(1+$A25)^2+$D$5/(1+$A25)^3+$E$5/(1+$A25)^4+($F$5+D$23*$F$5)/(1+$A25)^5 -> 1105.836 | E25: =$B$5/(1+$A25)^1+$C$5/(1+$A25)^2+$D$5/(1+$A25)^3+$E$5/(1+$A25)^4+($F$5+E$23*$F$5)/(1+$A25)^5 -> 1250.0173 | F25: =$B$5/(1+$A25)^1+$C$5/(1+$A25)^2+$D$5/(1+$A25)^3+$E$5/(1+$A25)^4+($F$5+F$23*$F$5)/(1+$A25)^5 -> 1394.1985
A26: 0.2 | B26: =$B$5/(1+$A26)^1+$C$5/(1+$A26)^2+$D$5/(1+$A26)^3+$E$5/(1+$A26)^4+($F$5+B$23*$F$5)/(1+$A26)^5 -> 683.55838 | C26: =$B$5/(1+$A26)^1+$C$5/(1+$A26)^2+$D$5/(1+$A26)^3+$E$5/(1+$A26)^4+($F$5+C$23*$F$5)/(1+$A26)^5 -> 800.10288 | D26: =$B$5/(1+$A26)^1+$C$5/(1+$A26)^2+$D$5/(1+$A26)^3+$E$5/(1+$A26)^4+($F$5+D$23*$F$5)/(1+$A26)^5 -> 916.64738 | E26: =$B$5/(1+$A26)^1+$C$5/(1+$A26)^2+$D$5/(1+$A26)^3+$E$5/(1+$A26)^4+($F$5+E$23*$F$5)/(1+$A26)^5 -> 1033.1919 | F26: =$B$5/(1+$A26)^1+$C$5/(1+$A26)^2+$D$5/(1+$A26)^3+$E$5/(1+$A26)^4+($F$5+F$23*$F$5)/(1+$A26)^5 -> 1149.7364
A27: 0.25 | B27: =$B$5/(1+$A27)^1+$C$5/(1+$A27)^2+$D$5/(1+$A27)^3+$E$5/(1+$A27)^4+($F$5+B$23*$F$5)/(1+$A27)^5 -> 577.8368 | C27: =$B$5/(1+$A27)^1+$C$5/(1+$A27)^2+$D$5/(1+$A27)^3+$E$5/(1+$A27)^4+($F$5+C$23*$F$5)/(1+$A27)^5 -> 672.864 | D27: =$B$5/(1+$A27)^1+$C$5/(1+$A27)^2+$D$5/(1+$A27)^3+$E$5/(1+$A27)^4+($F$5+D$23*$F$5)/(1+$A27)^5 -> 767.8912 | E27: =$B$5/(1+$A27)^1+$C$5/(1+$A27)^2+$D$5/(1+$A27)^3+$E$5/(1+$A27)^4+($F$5+E$23*$F$5)/(1+$A27)^5 -> 862.9184 | F27: =$B$5/(1+$A27)^1+$C$5/(1+$A27)^2+$D$5/(1+$A27)^3+$E$5/(1+$A27)^4+($F$5+F$23*$F$5)/(1+$A27)^5 -> 957.9456
A28: 0.3 | B28: =$B$5/(1+$A28)^1+$C$5/(1+$A28)^2+$D$5/(1+$A28)^3+$E$5/(1+$A28)^4+($F$5+B$23*$F$5)/(1+$A28)^5 -> 493.46056 | C28: =$B$5/(1+$A28)^1+$C$5/(1+$A28)^2+$D$5/(1+$A28)^3+$E$5/(1+$A28)^4+($F$5+C$23*$F$5)/(1+$A28)^5 -> 571.56599 | D28: =$B$5/(1+$A28)^1+$C$5/(1+$A28)^2+$D$5/(1+$A28)^3+$E$5/(1+$A28)^4+($F$5+D$23*$F$5)/(1+$A28)^5 -> 649.67142 | E28: =$B$5/(1+$A28)^1+$C$5/(1+$A28)^2+$D$5/(1+$A28)^3+$E$5/(1+$A28)^4+($F$5+E$23*$F$5)/(1+$A28)^5 -> 727.77685 | F28: =$B$5/(1+$A28)^1+$C$5/(1+$A28)^2+$D$5/(1+$A28)^3+$E$5/(1+$A28)^4+($F$5+F$23*$F$5)/(1+$A28)^5 -> 805.88228
A30: The shaded cell is tonight's base case. One glance shows what a five-point rate argument or a one-turn multiple argument is worth.

Sheet Annotations
A1: Annotations — what every formula is doing, in English
A3: PRESENT & FUTURE VALUE | B3: One machine, two directions. Forward: FV = PV × (1+r)^n — money grows. Backward: PV = FV ÷ (1+r)^n — a promise shrinks. The Valuation tab's 'discount factor' row is the backward gear: 1/(1+r)^n.
A4: NPV — net present value | B4: Every future cash flow pulled back to today and added up, plus the pulled-back sale. It answers: given my rate, what is this stream worth? Cell B12 on Valuation.
A5: TERMINAL VALUE | B5: We stop projecting at Yr 5 and pretend to sell: exit multiple × Yr-5 free cash flow. It is the model's biggest single assumption — B13 shows what share of the answer it carries. Expect 60%+. That is normal, and it is why you argue about multiples.
A6: IRR — internal rate of return | B6: The question flipped: given the price, what does the stream pay? Formally, the discount rate at which NPV equals zero. Excel's =IRR() solves it by trial and error, exactly like you would.
A7: EBITDA | B7: Earnings before interest, taxes, depreciation & amortization — tonight's stand-in for operating cash generation. Real diligence walks EBITDA down to true free cash flow; S05's cash-flow statement is the map.
A8: WHAT WE SIMPLIFIED | B8: No taxes, no depreciation schedule, no debt inside the business, mid-year timing ignored (all cash assumed to land on Dec 31). Each simplification is fixable — and each fix is a good workbook exercise.
A9: XNPV / XIRR | B9: Excel's =NPV() assumes the first cash flow is one full year away, and =IRR() assumes even yearly spacing. Real deals pay on real dates: =XNPV(rate, values, dates) and =XIRR(values, dates) take actual calendars. When money moves mid-year, they are the honest versions.
A10: COLOR CODE | B10: Blue = input, change freely. Black = formula, leave alone. Green = pulled from another tab. Yellow fill = the big levers.
A11: SOURCES | B11: All operating figures are course projections built for Fitler MBA S06 — assumptions to stress, not facts about any real business. Discount-rate context: the Spectrum of Returns (session deck, Act II), market yields as of early Aug 2026.
